setup.cfg
setup.py
json_logger/__init__.py
json_logger/json_logger_lib.py
json_logger.egg-info/PKG-INFO
json_logger.egg-info/SOURCES.txt
json_logger.egg-info/dependency_links.txt
json_logger.egg-info/top_level.txt