Metadata-Version: 1.1
Name: json-logger
Version: 0.0.1
Summary: Sending json to a logger
Home-page: https://github.com/tekton/python_json_logger
Author: Tyler Agee
Author-email: tyler@pyroturtle.com
License: MIT License
Keywords: operator
Platform: UNKNOWN
Classifier: Development Status :: 4 - Beta
Classifier: Intended Audience :: Developers
Classifier: License :: OSI Approved :: MIT License
Classifier: Programming Language :: Python
Classifier: Programming Language :: Python :: 2.7
Classifier: Topic :: Software Development :: Libraries :: Python Modules
